shownode/__init__
shownode/shownode.py
shownode-0.1.0.dist-info/entry_points.txt
shownode-0.1.0.dist-info/LICENSE
shownode-0.1.0.dist-info/WHEEL
shownode-0.1.0.dist-info/METADATA
shownode-0.1.0.dist-info/RECORD
