Metadata-Version: 2.1
Name: shownode
Version: 0.1.0
Summary: Connect to docker containers with open vnc ports
License: MIT
Author: dskard
Requires-Python: >=3.7,<4.0
Classifier: License :: OSI Approved :: MIT License
Classifier: Programming Language :: Python :: 3
Classifier: Programming Language :: Python :: 3.10
Classifier: Programming Language :: Python :: 3.7
Classifier: Programming Language :: Python :: 3.8
Classifier: Programming Language :: Python :: 3.9
